[
  {
    "id": "char-001",
    "name": "The Wanderer",
    "stats": {
      "health": "3 Red Hearts",
      "speed": "1.0",
      "damage": "3.5",
      "range": "6.5",
      "shotSpeed": "1.0",
      "luck": "0"
    },
    "startingItems": ["None"],
    "unlock": "Available from start",
    "details": "The Wanderer is the balanced starting character, perfect for beginners. With average stats across the board, they offer a straightforward introduction to the game mechanics without any special gimmicks. Great for learning the fundamentals before trying more challenging characters.",
    "image": "/assets/img/placeholders/character.svg"
  },
  {
    "id": "char-002",
    "name": "The Gambler",
    "stats": {
      "health": "2 Red Hearts",
      "speed": "1.1",
      "damage": "3.0",
      "range": "6.0",
      "shotSpeed": "1.0",
      "luck": "3"
    },
    "startingItems": ["Chaos Dice", "Lucky Coin"],
    "unlock": "Defeat the final boss 3 times",
    "details": "The Gambler lives and dies by chance. Starting with high luck and items that encourage risk-taking, this character rewards players who embrace randomness. The Chaos Dice can save bad runs or ruin good ones - use it wisely.",
    "image": "/assets/img/placeholders/character.svg"
  },
  {
    "id": "char-003",
    "name": "The Paladin",
    "stats": {
      "health": "4 Red Hearts",
      "speed": "0.9",
      "damage": "4.0",
      "range": "5.5",
      "shotSpeed": "0.9",
      "luck": "0"
    },
    "startingItems": ["Iron Heart", "Sacred Tears"],
    "unlock": "Complete 5 Angel Rooms without taking damage",
    "details": "A holy warrior with high health and damage but reduced mobility. The Paladin excels at tanking hits and dealing heavy damage. The Sacred Tears provide occasional burst damage, making them excellent for both crowds and bosses.",
    "image": "/assets/img/placeholders/character.svg"
  },
  {
    "id": "char-004",
    "name": "The Shadow",
    "stats": {
      "health": "1 Red Heart + 2 Soul Hearts",
      "speed": "1.3",
      "damage": "2.5",
      "range": "7.0",
      "shotSpeed": "1.2",
      "luck": "1"
    },
    "startingItems": ["Ethereal Cloak", "Speed Boots"],
    "unlock": "Beat the game without taking red heart damage",
    "details": "A speedy, evasive character that relies on dodging rather than tanking damage. The flight and spectral tears make navigation trivial, but low health means mistakes are costly. Mastering The Shadow teaches precision and patience.",
    "image": "/assets/img/placeholders/character.svg"
  },
  {
    "id": "char-005",
    "name": "The Berserker",
    "stats": {
      "health": "1 Red Heart",
      "speed": "1.2",
      "damage": "5.0",
      "range": "5.0",
      "shotSpeed": "0.8",
      "luck": "-1"
    },
    "startingItems": ["Berserker Rage", "Flame Aura"],
    "unlock": "Complete a run with half a heart or less for 3 floors",
    "details": "The ultimate high-risk, high-reward character. With massive damage but minimal health, The Berserker forces aggressive gameplay. The starting Berserker Rage activates immediately, and the Flame Aura provides melee crowd control.",
    "image": "/assets/img/placeholders/character.svg"
  },
  {
    "id": "char-006",
    "name": "The Alchemist",
    "stats": {
      "health": "2 Red Hearts",
      "speed": "1.0",
      "damage": "3.0",
      "range": "6.5",
      "shotSpeed": "1.0",
      "luck": "2"
    },
    "startingItems": ["Poison Vial", "Ancient Scroll"],
    "unlock": "Use 20 active items in a single run",
    "details": "A tactical character focused on status effects and active items. The Poison Vial makes every hit count over time, while the Ancient Scroll provides burst damage when needed. Requires strategic thinking about resource management.",
    "image": "/assets/img/placeholders/character.svg"
  },
  {
    "id": "char-007",
    "name": "The Mage",
    "stats": {
      "health": "1 Red Heart + 3 Soul Hearts",
      "speed": "0.95",
      "damage": "2.8",
      "range": "8.0",
      "shotSpeed": "1.3",
      "luck": "1"
    },
    "startingItems": ["Thunder Strike", "Tome of Shadows"],
    "unlock": "Collect 10 Library items",
    "details": "A powerful magic-user with long range and chain lightning effects. The Tome of Shadows helps with exploration, while Thunder Strike can clear entire rooms. Soul hearts provide good survivability despite low base health.",
    "image": "/assets/img/placeholders/character.svg"
  },
  {
    "id": "char-008",
    "name": "The Merchant",
    "stats": {
      "health": "3 Red Hearts",
      "speed": "1.05",
      "damage": "3.2",
      "range": "6.0",
      "shotSpeed": "1.0",
      "luck": "1"
    },
    "startingItems": ["Lucky Coin", "Magnetic Ring"],
    "unlock": "Spend 500 coins in shops",
    "details": "A character built around economic advantage. Starts with items that boost coin generation and collection. More money means more shop items, which can snowball into powerful runs. Great for players who enjoy the shopping meta.",
    "image": "/assets/img/placeholders/character.svg"
  },
  {
    "id": "char-009",
    "name": "The Guardian",
    "stats": {
      "health": "5 Red Hearts",
      "speed": "0.85",
      "damage": "3.0",
      "range": "5.0",
      "shotSpeed": "0.85",
      "luck": "0"
    },
    "startingItems": ["Celestial Orb", "Mirror Shield"],
    "unlock": "Complete a run without dying",
    "details": "The tankiest character available. With 5 hearts and defensive items, The Guardian can survive mistakes that would kill others. The low speed is a significant drawback, requiring careful positioning and planning.",
    "image": "/assets/img/placeholders/character.svg"
  },
  {
    "id": "char-010",
    "name": "The Trickster",
    "stats": {
      "health": "2 Red Hearts",
      "speed": "1.15",
      "damage": "3.0",
      "range": "6.0",
      "shotSpeed": "1.1",
      "luck": "2"
    },
    "startingItems": ["Dimensional Key", "Cursed Skull"],
    "unlock": "Find 10 secret rooms",
    "details": "A chaotic character that specializes in teleportation and room manipulation. The Dimensional Key provides access to special rooms, while the Cursed Skull adds unpredictability. Not for players who like consistency, but extremely fun for those who embrace chaos.",
    "image": "/assets/img/placeholders/character.svg"
  }
]
